{
    "name": "Symmetric",
    "version": {
        "major": 1,
        "minor": 0,
        "patch": 0
    },
    "keywords": [],
    "logoURI": "https://mytokenlist.com/image.png",
    "timestamp": "2024-07-02T12:33:57.164Z",
    "tokens": [
        {
            "chainId": 40,
            "address": "0xd5f2a24199C3DFc44C1Bf8B1C01aB147809434Ca",
            "name": "Symmetric on Telos",
            "symbol": "tSYMM",
            "decimals": 18,
            "logoURI": "https://raw.githubusercontent.com/centfinance/tokenlists/main/src/assets/images/tokens/TSYMM.png"
        },
        {
            "chainId": 40,
            "address": "0xbf0FA44e5611C31429188B7dcc59ffe794D1980e",
            "name": "Symmetric 80 TSYMM 20 WTLOS",
            "symbol": "S-80TSYMM-20WTLOS",
            "decimals": 18,
            "logoURI": "https://raw.githubusercontent.com/centfinance/tokenlists/main/src/assets/images/tokens/0xbf0fa44e5611c31429188b7dcc59ffe794d1980e.png"
        },
        {
            "chainId": 40,
            "address": "0xD102cE6A4dB07D247fcc28F366A623Df0938CA9E",
            "name": "Wrapped TLOS",
            "symbol": "WTLOS",
            "decimals": 18,
            "logoURI": "https://raw.githubusercontent.com/telosnetwork/token-list/main/logos/wtlos.png"
        },
        {
            "chainId": 40,
            "address": "0xB4B01216a5Bc8F1C8A33CD990A1239030E60C905",
            "name": "Staked TLOS",
            "symbol": "STLOS",
            "decimals": 18,
            "logoURI": "https://raw.githubusercontent.com/telosnetwork/token-list/main/logos/stlos.png"
        },
        {
            "chainId": 40,
            "address": "0x8D97Cea50351Fb4329d591682b148D43a0C3611b",
            "name": "USD Coin",
            "symbol": "USDC",
            "decimals": 6,
            "logoURI": "https://assets-cdn.trustwallet.com/blockchains/ethereum/assets/0xA0b86991c6218b36c1d19D4a2e9Eb0cE3606eB48/logo.png"
        },
        {
            "chainId": 40,
            "address": "0x975Ed13fa16857E83e7C493C7741D556eaaD4A3f",
            "name": "Tether USD",
            "symbol": "USDT",
            "decimals": 6,
            "logoURI": "https://assets-cdn.trustwallet.com/blockchains/ethereum/assets/0xdAC17F958D2ee523a2206206994597C13D831ec7/logo.png"
        },
        {
            "chainId": 40,
            "address": "0x8f7D64ea96D729EF24a0F30b4526D47b80d877B9",
            "name": "USDM Stablecoin",
            "symbol": "USDM",
            "decimals": 18,
            "logoURI": "https://raw.githubusercontent.com/swapsicledex/swapsicle-token-list/master/logos/telos/0x8f7D64ea96D729EF24a0F30b4526D47b80d877B9/logo.png"
        },
        {
            "chainId": 40,
            "address": "0x7627b27594bc71e6Ab0fCE755aE8931EB1E12DAC",
            "name": "Bitcoin",
            "symbol": "BTC.b",
            "decimals": 8,
            "logoURI": "https://raw.githubusercontent.com/telosnetwork/token-list/main/logos/BTC.b.png"
        },
        {
            "chainId": 40,
            "address": "0xA0fB8cd450c8Fd3a11901876cD5f17eB47C6bc50",
            "name": "Ether",
            "symbol": "ETH",
            "decimals": 18,
            "logoURI": "https://cryptologos.cc/logos/ethereum-eth-logo.png"
        },
        {
            "chainId": 40,
            "address": "0x26Ed0F16e777C94A6FE798F9E20298034930Bae8",
            "name": "BNB",
            "symbol": "BNB",
            "decimals": 18,
            "logoURI": "https://raw.githubusercontent.com/elkfinance/tokens/main/logos/ftm/0xD67de0e0a0Fd7b15dC8348Bb9BE742F3c5850454/logo.png"
        },
        {
            "chainId": 40,
            "address": "0x568524DA340579887db50Ecf602Cd1BA8451b243",
            "name": "MST",
            "symbol": "MST",
            "decimals": 18,
            "logoURI": "https://raw.githubusercontent.com/swapsicledex/swapsicle-token-list/master/logos/telos/0x568524DA340579887db50Ecf602Cd1BA8451b243/logo.png"
        },
        {
            "chainId": 40,
            "address": "0x058D4893eFa235D86CcEeD5a7Eef0809B76c8c66",
            "name": "USDC-USDT Stable Pool",
            "symbol": "USDC-USDT",
            "decimals": 18,
            "logoURI": "https://raw.githubusercontent.com/centfinance/tokenlists/main/src/assets/images/tokens/USDC-USDT.png"
        },
        {
            "chainId": 40,
            "address": "0x7d94D2F6f91ED5ED0104D89B3D263026D990Ac5f",
            "name": "ReactorFusion TLOS",
            "symbol": "rfTLOS",
            "decimals": 18,
            "logoURI": "https://raw.githubusercontent.com/telosnetwork/token-list/main/logos/telos.png"
        },
        {
            "chainId": 40,
            "address": "0xA6A5FE78A12ae40BEd9300dA6DE624c089F77ac2",
            "name": "ReactorFusion USDC",
            "symbol": "rfUSDC",
            "decimals": 6,
            "logoURI": "https://assets-cdn.trustwallet.com/blockchains/ethereum/assets/0xA0b86991c6218b36c1d19D4a2e9Eb0cE3606eB48/logo.png"
        },
        {
            "chainId": 40,
            "address": "0xcE08cFf82fB1B6902a7Dca2Ccd2d164Bc2B5B1Cd",
            "name": "ReactorFusion ETH",
            "symbol": "rfETH",
            "decimals": 18,
            "logoURI": "https://cryptologos.cc/logos/ethereum-eth-logo.png"
        },
        {
            "chainId": 40,
            "address": "0x3D187a993D946f196429c83f9A1831513AC2D2BE",
            "name": "ReactorFusion USDT",
            "symbol": "rfUSDT",
            "decimals": 6,
            "logoURI": "https://assets-cdn.trustwallet.com/blockchains/ethereum/assets/0xdAC17F958D2ee523a2206206994597C13D831ec7/logo.png"
        },
        {
            "chainId": 40,
            "address": "0xb99C43d3bce4c8Ad9B95a4A178B04a7391b2a6EB",
            "name": "ReactorFusion",
            "symbol": "RF",
            "decimals": 18,
            "logoURI": "https://raw.githubusercontent.com/centfinance/tokenlists/main/src/assets/images/tokens/RF.png"
        },
        {
            "chainId": 40,
            "address": "0xb754619F355eF11cb36cce70784767bA92264330",
            "name": "Trump",
            "symbol": "Trump",
            "decimals": 6,
            "logoURI": "https://raw.githubusercontent.com/swapsicledex/swapsicle-token-list/master/logos/telos/0xb754619F355eF11cb36cce70784767bA92264330/logo.png"
        },
        {
            "chainId": 40,
            "address": "0xe9F5Cb51f507436E3DdDA226c8d3dF62FA3E6368",
            "name": "Commander",
            "symbol": "CMDR",
            "decimals": 18,
            "logoURI": "https://raw.githubusercontent.com/centfinance/tokenlists/main/src/assets/images/tokens/CMDR.png"
        },
        {
            "chainId": 40,
            "address": "0xa3b4AeE7B43B2Fb390420c411ec180B0ae87E9da",
            "name": "KINDNESS FOR SOULS",
            "symbol": "SOULS ",
            "decimals": 18,
            "logoURI": "https://raw.githubusercontent.com/centfinance/tokenlists/main/src/assets/images/tokens/SOULS.png"
        },
        {
            "chainId": 40,
            "address": "0x143AA2070E3b5414c68A93Ba0A99BAC8847Cbe99",
            "name": "KINDNESS FOR THE SOUL",
            "symbol": "KINDs",
            "decimals": 18,
            "logoURI": "https://raw.githubusercontent.com/centfinance/tokenlists/main/src/assets/images/tokens/KINDS.png"
        },
        {
            "chainId": 40,
            "address": "0xfdfF55a36f3dd3942A4Ac5Aebe68972d57296925",
            "name": "Wrapped USK",
            "symbol": "wUSK",
            "decimals": 18,
            "logoURI": "https://raw.githubusercontent.com/centfinance/tokenlists/main/src/assets/images/tokens/WUSK.png"
        },
        {
            "chainId": 40,
            "address": "0xce436C598027B39bcC80094B670A60184a290Fe1",
            "name": "ALI حيدر",
            "symbol": "ALI",
            "decimals": 18,
            "logoURI": "https://raw.githubusercontent.com/centfinance/tokenlists/main/src/assets/images/tokens/ALI.png"
        },
        {
            "chainId": 40,
            "address": "0x836EfDc24A00d42160AF3eF144Af96CBc0c09aa0",
            "name": "SOULS USD",
            "symbol": "SUSD",
            "decimals": 18,
            "logoURI": "https://raw.githubusercontent.com/centfinance/tokenlists/main/src/assets/images/tokens/SUSD.png"
        },
        {
            "chainId": 40,
            "address": "0x953808eF6BE397925f71Ec0e8892e246882e4804",
            "name": "ERC4626-Wrapped Meridian Lend USDC",
            "symbol": "woUSDC",
            "decimals": 6,
            "logoURI": "https://assets-cdn.trustwallet.com/blockchains/ethereum/assets/0xA0b86991c6218b36c1d19D4a2e9Eb0cE3606eB48/logo.png"
        },
        {
            "chainId": 40,
            "address": "0x181F14262E2EFD4DF781079437eBa1AeD3343898",
            "name": "ERC4626-Wrapped Meridian Lend USDT",
            "symbol": "woUSDT",
            "decimals": 6,
            "logoURI": "https://assets-cdn.trustwallet.com/blockchains/ethereum/assets/0xdAC17F958D2ee523a2206206994597C13D831ec7/logo.png"
        },
        {
            "chainId": 40,
            "address": "0x8eDc3bDd08980d5F6672F243CEbC58c6C117956A",
            "name": "ERC4626-Wrapped Meridian Lend USDM",
            "symbol": "woUSDM",
            "decimals": 18,
            "logoURI": "https://raw.githubusercontent.com/swapsicledex/swapsicle-token-list/master/logos/telos/0x8f7D64ea96D729EF24a0F30b4526D47b80d877B9/logo.png"
        },
        {
            "chainId": 40,
            "address": "0x47355ba67A884FE9AA1B2CB774bF9128E7e0598a",
            "name": "Meridian Yield Accelerated USDC Pool",
            "symbol": "myaUSDC",
            "decimals": 18,
            "logoURI": "https://assets-cdn.trustwallet.com/blockchains/ethereum/assets/0xA0b86991c6218b36c1d19D4a2e9Eb0cE3606eB48/logo.png"
        },
        {
            "chainId": 40,
            "address": "0x0FC39136421aDFD8466E8909de8a7EcDf54f8d31",
            "name": "Meridian Yield Accelerated USDT Pool",
            "symbol": "myaUSDT",
            "decimals": 18,
            "logoURI": "https://assets-cdn.trustwallet.com/blockchains/ethereum/assets/0xdAC17F958D2ee523a2206206994597C13D831ec7/logo.png"
        },
        {
            "chainId": 40,
            "address": "0x73DFDF2b9A5eD7B032Fa50Dce81De350Aa209Aad",
            "name": "Meridian Yield Accelerated USDM Pool",
            "symbol": "myaUSDM",
            "decimals": 18,
            "logoURI": "https://raw.githubusercontent.com/swapsicledex/swapsicle-token-list/master/logos/telos/0x8f7D64ea96D729EF24a0F30b4526D47b80d877B9/logo.png"
        },
        {
            "chainId": 41,
            "address": "0x7e3dAe5fd8FaED7C3Bef04F987c2eF68A9A350A4",
            "name": "Symmetric",
            "symbol": "SYMM",
            "decimals": 18,
            "logoURI": "https://raw.githubusercontent.com/centfinance/tokenlists/main/src/assets/images/tokens/0x7e3dAe5fd8FaED7C3Bef04F987c2eF68A9A350A4.png"
        },
        {
            "chainId": 41,
            "address": "0xF5Dd4A1fCE57D9aCd7a4fEF03709402014b56813",
            "name": "Wrapped TLOS",
            "symbol": "WTLOS",
            "decimals": 18,
            "logoURI": "https://raw.githubusercontent.com/telosnetwork/token-list/main/logos/telos.png"
        },
        {
            "chainId": 41,
            "address": "0xa9991E4daA44922D00a78B6D986cDf628d46C4DD",
            "name": "Staked TLOS",
            "symbol": "STLOS",
            "decimals": 18,
            "logoURI": "https://raw.githubusercontent.com/centfinance/tokenlists/main/src/assets/images/tokens/0x98BD57444603C66b736Fd0AeFCBE494c8Ee32C71.png"
        },
        {
            "chainId": 41,
            "address": "0xF9485b3fffd191e28a089C21cD745cc228a181E3",
            "name": "USDC",
            "symbol": "USDC",
            "decimals": 6,
            "logoURI": "https://assets-cdn.trustwallet.com/blockchains/ethereum/assets/0xA0b86991c6218b36c1d19D4a2e9Eb0cE3606eB48/logo.png"
        },
        {
            "chainId": 41,
            "address": "0x39D33701581EE17DfF7dBeEcCC35210aEE7B0417",
            "name": "USDT",
            "symbol": "USDT",
            "decimals": 6,
            "logoURI": "https://assets-cdn.trustwallet.com/blockchains/ethereum/assets/0xdAC17F958D2ee523a2206206994597C13D831ec7/logo.png"
        },
        {
            "chainId": 82,
            "address": "0x663345e09F4F4437F3D5df39BA5c2B5690532206",
            "name": "Symmetric on Meter",
            "symbol": "mSYMM",
            "decimals": 18,
            "logoURI": "https://raw.githubusercontent.com/centfinance/tokenlists/main/src/assets/images/tokens/mSYMM.png"
        },
        {
            "chainId": 82,
            "address": "0x228ebBeE999c6a7ad74A6130E81b12f9Fe237Ba3",
            "name": "MeterGov",
            "symbol": "MTRG",
            "decimals": 18,
            "logoURI": "https://raw.githubusercontent.com/meterio/token-list/master/generated/token-logos/meter/0x228ebbee999c6a7ad74a6130e81b12f9fe237ba3.png"
        },
        {
            "chainId": 82,
            "address": "0x215d603293357ca222bE92A1bf75eEc38DeF0aad",
            "name": "Staked MTRG",
            "symbol": "stMTRG",
            "decimals": 18,
            "logoURI": "https://raw.githubusercontent.com/meterio/token-list/master/generated/token-logos/meter/0x215d603293357ca222be92a1bf75eec38def0aad.png"
        },
        {
            "chainId": 82,
            "address": "0xE2dE616fBD8cb9180B26FcFB1B761A232FE56717",
            "name": "Wrapped liquid staked MTRG",
            "symbol": "wstMTRG",
            "decimals": 18,
            "logoURI": "https://raw.githubusercontent.com/meterio/token-list/master/generated/token-logos/meter/0xe2de616fbd8cb9180b26fcfb1b761a232fe56717.png"
        },
        {
            "chainId": 82,
            "address": "0x8BF591Eae535f93a242D5A954d3Cde648b48A5A8",
            "name": "Sumerian USD",
            "symbol": "suUSD",
            "decimals": 18,
            "logoURI": "https://raw.githubusercontent.com/meterio/token-list/master/generated/token-logos/meter/0x8bf591eae535f93a242d5a954d3cde648b48a5a8.png"
        },
        {
            "chainId": 82,
            "address": "0x983147FB73A45FC7F8B4DFA1cd61Bdc7b111e5b6",
            "name": "ETH from Ethereum on Meter",
            "symbol": "ETH",
            "decimals": 18,
            "logoURI": "https://raw.githubusercontent.com/meterio/token-list/master/generated/token-logos/meter/0x983147fb73a45fc7f8b4dfa1cd61bdc7b111e5b6.png"
        },
        {
            "chainId": 82,
            "address": "0xD86e243FC0007e6226B07c9A50C9d70D78299EB5",
            "name": "Wrapped USDC from Ethereum",
            "symbol": "USDC.eth",
            "decimals": 6,
            "logoURI": "https://raw.githubusercontent.com/meterio/token-list/master/generated/token-logos/meter/0xd86e243fc0007e6226b07c9a50c9d70d78299eb5.png"
        },
        {
            "chainId": 82,
            "address": "0x5Fa41671c48e3C951AfC30816947126CCC8C162e",
            "name": "Wrapped USDT from Ethereum on Meter",
            "symbol": "USDT.eth",
            "decimals": 6,
            "logoURI": "https://raw.githubusercontent.com/meterio/token-list/master/generated/token-logos/meter/0x5fa41671c48e3c951afc30816947126ccc8c162e.png"
        },
        {
            "chainId": 82,
            "address": "0x160361ce13ec33C993b5cCA8f62B6864943eb083",
            "name": "Wrapped MTR",
            "symbol": "WMTR",
            "decimals": 18,
            "logoURI": "https://raw.githubusercontent.com/meterio/token-list/master/data/MTR/logo.png"
        },
        {
            "chainId": 82,
            "address": "0xF0E86246519Be0810C9FAfc8430C49799985aAA8",
            "name": "BNB from BSC on Meter",
            "symbol": "BNB",
            "decimals": 18,
            "logoURI": "https://raw.githubusercontent.com/meterio/token-list/master/generated/token-logos/meter/0xf0e86246519be0810c9fafc8430c49799985aaa8.png"
        },
        {
            "chainId": 82,
            "address": "0x1fF97aBe4C5A4b7fF90949B637e71626BEF0DCee",
            "name": "USDT-USDC-suUSD Stable Pool",
            "symbol": "USDT-USDC-suUSD",
            "decimals": 18,
            "logoURI": "https://raw.githubusercontent.com/centfinance/tokenlists/main/src/assets/images/tokens/0x1ff97abe4c5a4b7ff90949b637e71626bef0dcee.png"
        },
        {
            "chainId": 82,
            "address": "0x5647f6cc997e45b81d786bAa9ECd8A1ad40Ef25f",
            "name": "MST",
            "symbol": "MST",
            "decimals": 18,
            "logoURI": "https://raw.githubusercontent.com/swapsicledex/swapsicle-token-list/master/logos/telos/0x568524DA340579887db50Ecf602Cd1BA8451b243/logo.png"
        },
        {
            "chainId": 82,
            "address": "0x2077a828fD58025655335a8756dBcfEB7e5BeC46",
            "name": "MTRG-wstMTRG Stable Pool",
            "symbol": "MTRG-wstMTRG",
            "decimals": 18,
            "logoURI": "https://raw.githubusercontent.com/centfinance/tokenlists/main/src/assets/images/tokens/MTRG-wstMTRG.png"
        },
        {
            "chainId": 11822,
            "address": "0x23625fF2AEC3A5e3459a9FD75661a135c567B072",
            "name": "USD Coin",
            "symbol": "USDC",
            "decimals": 18,
            "logoURI": "https://assets-cdn.trustwallet.com/blockchains/ethereum/assets/0xA0b86991c6218b36c1d19D4a2e9Eb0cE3606eB48/logo.png"
        },
        {
            "chainId": 11822,
            "address": "0x729C714A7cbF5599AA121489b0386537b1347e5e",
            "name": "Tether",
            "symbol": "USDT",
            "decimals": 18,
            "logoURI": "https://assets-cdn.trustwallet.com/blockchains/ethereum/assets/0xdAC17F958D2ee523a2206206994597C13D831ec7/logo.png"
        },
        {
            "chainId": 11822,
            "address": "0x4a869ed6b3f74dC41537EF27e8eB3A8676AE4614",
            "name": "Symmetric on Artela",
            "symbol": "aSYMM",
            "decimals": 18,
            "logoURI": "https://raw.githubusercontent.com/centfinance/tokenlists/main/src/assets/images/tokens/aSYMM.png"
        },
        {
            "chainId": 11822,
            "address": "0xaDCd43c78A914c6B14171aB1380bCFcfa25cd3AD",
            "name": "Wrapped Art",
            "symbol": "wART",
            "decimals": 18,
            "logoURI": "https://raw.githubusercontent.com/centfinance/tokenlists/main/src/assets/images/tokens/WART.png"
        },
        {
            "chainId": 11822,
            "address": "0x7bf8b8Da6E71ebc92383dAf6f32F82b073a303cD",
            "name": "Ethereum",
            "symbol": "ETH",
            "decimals": 18,
            "logoURI": "https://cryptologos.cc/logos/ethereum-eth-logo.png"
        },
        {
            "chainId": 11822,
            "address": "0x9c9dF9E55f4770132e586f32741D7e4F80C39B2a",
            "name": "Wrapped Bitcoin",
            "symbol": "WBTC",
            "decimals": 18,
            "logoURI": "https://cryptologos.cc/logos/bitcoin-btc-logo.png"
        },
        {
            "chainId": 11822,
            "address": "0xDFEe275C6491Be5833404d6134a08d81e46b08D8",
            "name": "Artela USD",
            "symbol": "aUSD",
            "decimals": 6,
            "logoURI": "https://assets-cdn.trustwallet.com/blockchains/ethereum/assets/0xA0b86991c6218b36c1d19D4a2e9Eb0cE3606eB48/logo.png"
        }
    ]
}